negromate/songs/__init__.py
negromate/songs/karaoke_templates.py
negromate/songs/loader.py
negromate/songs/utils.py
negromate/songs/commands/__init__.py
negromate/songs/commands/config.py
negromate/songs/commands/songs.py
negromate/songs/commands/thumbnail.py
negromate.songs-1.5.dist-info/LICENSE.txt
negromate.songs-1.5.dist-info/METADATA
negromate.songs-1.5.dist-info/WHEEL
negromate.songs-1.5.dist-info/entry_points.txt
negromate.songs-1.5.dist-info/top_level.txt
negromate.songs-1.5.dist-info/zip-safe
negromate.songs-1.5.dist-info/RECORD
