Metadata-Version: 2.1
Name: negromate.songs
Version: 1.5
Summary: NegroMate karaoke song database library
Home-page: https://negromate.rocks
Author: Ales (Shagi) Zabala Alava
Author-email: shagi@gisa-elkartea.org
License: GPLv3
Classifier: Development Status :: 5 - Production/Stable
Classifier: License :: OSI Approved :: GNU General Public License v3 or later (GPLv3+)
Classifier: Programming Language :: Python :: 3
Classifier: Topic :: Games/Entertainment
Requires-Python: >=3.4
License-File: LICENSE.txt
Requires-Dist: importlib-metadata
Requires-Dist: webvtt-py
Requires-Dist: asstosrt==0.1.6
Requires-Dist: srt==3.5.3
Requires-Dist: ass==0.5.2
